dscontrib/__init__.py
dscontrib/bmiroglio/__init__.py
dscontrib/bmiroglio/search_ads.py
dscontrib/flawrence/__init__.py
dscontrib/flawrence/bq_experiment.py
dscontrib/flawrence/consistency_checks.py
dscontrib/flawrence/mobile.py
dscontrib/flawrence/plot_experiments.py
dscontrib/flawrence/power_analysis.py
dscontrib/flawrence/util.py
dscontrib/gkaberere/__init__.py
dscontrib/gkaberere/google_cloud_toolkit.py
dscontrib/jmccrosky/__init__.py
dscontrib/jmccrosky/anomdtct/__init__.py
dscontrib/jmccrosky/anomdtct/data.py
dscontrib/jmccrosky/anomdtct/forecast.py
dscontrib/jmccrosky/anomdtct/pipeline.py
dscontrib/jmccrosky/forecast/__init__.py
dscontrib/jmccrosky/forecast/data.py
dscontrib/jmccrosky/forecast/modeling.py
dscontrib/jmccrosky/forecast/models.py
dscontrib/jmccrosky/forecast/output.py
dscontrib/jmccrosky/forecast/pipeline.py
dscontrib/jmccrosky/forecast/utils.py
dscontrib/jmccrosky/forecast/validations.py
dscontrib/jmccrosky/gudnightly/__init__.py
dscontrib/jmccrosky/gudnightly/data.py
dscontrib/jmccrosky/gudnightly/metrics.py
dscontrib/jmccrosky/gudnightly/plots.py
dscontrib/jmccrosky/gudnightly/usage_criteria.py
dscontrib/jmccrosky/gudnightly/utils.py
dscontrib/jmccrosky/tableutils/__init__.py
dscontrib/jmccrosky/tableutils/tables.py
dscontrib/shong/__init__.py
dscontrib/shong/activitystream.py
dscontrib/shong/constants.py
dscontrib/shong/experiments.py
dscontrib/shong/util.py
dscontrib/tdsmith/__init__.py
dscontrib/tdsmith/luigi.py
dscontrib/wbeard/__init__.py
dscontrib/wbeard/altair_utils.py
dscontrib/wbeard/bootstrap.py
dscontrib/wbeard/bq_utils.py
dscontrib/wbeard/buildhub_utils.py
dscontrib/wbeard/cache.py
dscontrib/wbeard/cluster.py
dscontrib/wbeard/data_structures.py
dscontrib/wbeard/pandas_utils.py
dscontrib/wbeard/plot_utils.py
dscontrib/wbeard/test_utils.py
dscontrib/wbeard/utils.py
dscontrib-20201209022658.dist-info/LICENSE
dscontrib-20201209022658.dist-info/METADATA
dscontrib-20201209022658.dist-info/WHEEL
dscontrib-20201209022658.dist-info/top_level.txt
dscontrib-20201209022658.dist-info/RECORD
