Metadata-Version: 2.1
Name: dscontrib
Version: 20201209022658
Summary: A Python library for Mozilla Data Science code snippets
Home-page: https://github.com/mozilla/dscontrib
Author: Mozilla Data Science team
Author-email: fx-data-dev@mozilla.org
License: UNKNOWN
Platform: UNKNOWN
Requires-Dist: numpy
Requires-Dist: pandas
Requires-Dist: scipy
Requires-Dist: mozanalysis
Provides-Extra: luigi
Requires-Dist: attrs ; extra == 'luigi'
Requires-Dist: luigi ; extra == 'luigi'
Requires-Dist: google-cloud-bigquery ; extra == 'luigi'
Requires-Dist: google-cloud-storage ; extra == 'luigi'
Requires-Dist: pytz ; extra == 'luigi'
